MANIFEST.in
setup.cfg
setup.py
selenose/__init__.py
selenose/cases.py
selenose/configs.py
selenose/plugins.py
selenose/server.py
selenose.egg-info/PKG-INFO
selenose.egg-info/SOURCES.txt
selenose.egg-info/dependency_links.txt
selenose.egg-info/entry_points.txt
selenose.egg-info/not-zip-safe
selenose.egg-info/requires.txt
selenose.egg-info/top_level.txt
selenose/libs/__init__.py
selenose/tasks/__init__.py
selenose/tasks/selenium_driver.py
selenose/tasks/selenium_server.py