Metadata-Version: 1.0
Name: selenose
Version: 1.3
Summary: Selenium plugin for nose and django-jenkins
Home-page: https://github.com/shiningpanda/selenose/
Author: ShiningPanda
Author-email: developers@shiningpanda.com
License: GNU Affero General Public License
Download-URL: http://pypi.python.org/pypi/selenose/
Platform: UNKNOWN
Classifier: Development Status :: 5 - Production/Stable
Classifier: Environment :: Plugins
Classifier: Framework :: Django
Classifier: Intended Audience :: Developers
Classifier: Operating System :: OS Independent
Classifier: License :: OSI Approved :: GNU Library or Lesser General Public License (LGPL)
Classifier: Natural Language :: English
Classifier: Programming Language :: Python
Classifier: Topic :: Software Development :: Testing
